timepix_geometry_correction/__init__.py
timepix_geometry_correction/__main__.py
timepix_geometry_correction/config.py
timepix_geometry_correction/correct.py
timepix_geometry_correction/loading.py
timepix_geometry_correction/_version.py
timepix_geometry_correction-0.2.0.dev7.dist-info/METADATA
timepix_geometry_correction-0.2.0.dev7.dist-info/WHEEL
timepix_geometry_correction-0.2.0.dev7.dist-info/entry_points.txt
timepix_geometry_correction-0.2.0.dev7.dist-info/licenses/LICENSE
timepix_geometry_correction-0.2.0.dev7.dist-info/RECORD
